Metadata-Version: 2.1
Name: xwdMath
Version: 1.0
Summary: 对外发布的模块
Home-page: UNKNOWN
Author: xwd
Author-email: 993@qq.com
License: UNKNOWN
Platform: UNKNOWN
